{
  "ogmoVersion": "3.4.0-hubol",
  "width": 256,
  "height": 256,
  "offsetX": 0,
  "offsetY": 0,
  "layers": [
    {
      "name": "Entities",
      "_eid": "55827504",
      "offsetX": 0,
      "offsetY": 0,
      "gridCellWidth": 8,
      "gridCellHeight": 8,
      "gridCellsX": 32,
      "gridCellsY": 32,
      "entities": [
        {
          "name": "Block",
          "id": 0,
          "_eid": "55823268",
          "x": 0,
          "y": 0,
          "width": 256,
          "height": 64,
          "originX": 0,
          "originY": 0,
          "values": {"name": "", "depth": 0}
        },
        {
          "name": "Block",
          "id": 1,
          "_eid": "55823268",
          "x": 0,
          "y": 192,
          "width": 256,
          "height": 64,
          "originX": 0,
          "originY": 0,
          "values": {"name": "", "depth": 0}
        },
        {
          "name": "Block",
          "id": 2,
          "_eid": "55823268",
          "x": 0,
          "y": 64,
          "width": 16,
          "height": 128,
          "originX": 0,
          "originY": 0,
          "values": {"name": "", "depth": 0}
        },
        {
          "name": "Block",
          "id": 3,
          "_eid": "55823268",
          "x": 240,
          "y": 64,
          "width": 16,
          "height": 128,
          "originX": 0,
          "originY": 0,
          "values": {"name": "", "depth": 0}
        },
        {
          "name": "Door",
          "id": 4,
          "_eid": "55913988",
          "x": 32,
          "y": 160,
          "originX": 0,
          "originY": 0,
          "values": {"levelName": "GiantsTown", "checkpointName": "FromRestaurant", "name": "", "depth": 0}
        },
        {
          "name": "Player",
          "id": 5,
          "_eid": "55988047",
          "x": 88,
          "y": 192,
          "originX": 11,
          "originY": 27,
          "values": {"faceRight": true, "name": "", "depth": 0}
        },
        {
          "name": "Anchor",
          "id": 6,
          "_eid": "25979726",
          "x": 192,
          "y": 166,
          "originX": 0,
          "originY": 0,
          "values": {"name": "Salad", "depth": 0}
        },
        {
          "name": "PipeHorizontal",
          "id": 7,
          "_eid": "55841307",
          "x": 124,
          "y": 172,
          "width": 88,
          "originX": 0,
          "originY": 0,
          "values": {"visible": false, "name": "", "depth": 0}
        },
        {
          "name": "Region",
          "id": 8,
          "_eid": "25971607",
          "x": 64,
          "y": 80,
          "width": 72,
          "height": 72,
          "originX": 0,
          "originY": 0,
          "values": {"name": "MirrorRegion", "depth": 0}
        },
        {
          "name": "PipeHorizontal",
          "id": 9,
          "_eid": "55841307",
          "x": 26,
          "y": 108,
          "width": 28,
          "originX": 0,
          "originY": 0,
          "values": {"visible": false, "name": "", "depth": 0}
        }
      ]
    },
    {
      "name": "FrontDecals",
      "_eid": "23130474",
      "offsetX": 0,
      "offsetY": 0,
      "gridCellWidth": 8,
      "gridCellHeight": 8,
      "gridCellsX": 32,
      "gridCellsY": 32,
      "decals": [],
      "folder": "../../src/images"
    },
    {
      "name": "TerrainDecals",
      "_eid": "53244458",
      "offsetX": 0,
      "offsetY": 0,
      "gridCellWidth": 8,
      "gridCellHeight": 8,
      "gridCellsX": 32,
      "gridCellsY": 32,
      "decals": [
        {
          "x": 192,
          "y": -16,
          "scaleX": 1,
          "scaleY": 1,
          "rotation": 0,
          "texture": "giants/food stash.png",
          "originX": 0.5,
          "originY": 0,
          "values": {"name": ""}
        },
        {
          "x": 168,
          "y": 183,
          "scaleX": 1,
          "scaleY": 1,
          "rotation": 0,
          "texture": "giants/diner table.png",
          "originX": 0.5,
          "originY": 0.5,
          "values": {"name": ""}
        },
        {
          "x": 48,
          "y": 192,
          "scaleX": 1,
          "scaleY": 1,
          "rotation": 0,
          "texture": "ornate carpet.png",
          "originX": 0.5,
          "originY": 0,
          "values": {"name": ""}
        },
        {
          "x": 226,
          "y": 194,
          "scaleX": 1,
          "scaleY": 1,
          "rotation": 0,
          "texture": "pottery orange damaged.png",
          "originX": 0.5,
          "originY": 1,
          "values": {"name": ""}
        },
        {
          "x": 40,
          "y": 112,
          "scaleX": 1,
          "scaleY": 1,
          "rotation": 0,
          "texture": "light shelf.png",
          "originX": 0.5,
          "originY": 0.5,
          "values": {"name": ""}
        },
        {
          "x": 32,
          "y": 102,
          "scaleX": 1,
          "scaleY": 1,
          "rotation": 0,
          "texture": "rose vase.png",
          "originX": 0.5,
          "originY": 0.5,
          "values": {"name": ""}
        }
      ],
      "folder": "../../src/images"
    },
    {
      "name": "BackgroundDecals",
      "_eid": "03531763",
      "offsetX": 0,
      "offsetY": 0,
      "gridCellWidth": 8,
      "gridCellHeight": 8,
      "gridCellsX": 32,
      "gridCellsY": 32,
      "decals": [
        {
          "x": 24,
          "y": 88,
          "scaleX": 1,
          "scaleY": 1,
          "rotation": 0,
          "texture": "cloud long.png",
          "originX": 0.5,
          "originY": 0.5,
          "values": {"name": ""}
        },
        {
          "x": 64,
          "y": 136,
          "scaleX": 1,
          "scaleY": 1,
          "rotation": 0,
          "texture": "cloud long.png",
          "originX": 0.5,
          "originY": 0.5,
          "values": {"name": ""}
        },
        {
          "x": 144,
          "y": 96,
          "scaleX": 1,
          "scaleY": 1,
          "rotation": 0,
          "texture": "cloud long.png",
          "originX": 0.5,
          "originY": 0.5,
          "values": {"name": ""}
        },
        {
          "x": 240,
          "y": 152,
          "scaleX": 1,
          "scaleY": 1,
          "rotation": 0,
          "texture": "cloud long.png",
          "originX": 0.5,
          "originY": 0.5,
          "values": {"name": ""}
        },
        {
          "x": 240,
          "y": 72,
          "scaleX": 1,
          "scaleY": 1,
          "rotation": 0,
          "texture": "cloud long.png",
          "originX": 0.5,
          "originY": 0.5,
          "values": {"name": ""}
        },
        {
          "x": 152,
          "y": 168,
          "scaleX": 1,
          "scaleY": 1,
          "rotation": 0,
          "texture": "cloud long.png",
          "originX": 0.5,
          "originY": 0.5,
          "values": {"name": ""}
        },
        {
          "x": 32,
          "y": 190,
          "scaleX": 1,
          "scaleY": 1,
          "rotation": 0,
          "texture": "cloud long.png",
          "originX": 0.5,
          "originY": 0.5,
          "values": {"name": ""}
        }
      ],
      "folder": "..\\..\\src\\images"
    },
    {
      "name": "Parallax1Decals",
      "_eid": "86920620",
      "offsetX": 0,
      "offsetY": 0,
      "gridCellWidth": 8,
      "gridCellHeight": 8,
      "gridCellsX": 32,
      "gridCellsY": 32,
      "decals": [],
      "folder": "../../src/images"
    }
  ]
}